flask_auditor/__init__.py
flask_auditor/attributes.py
flask_auditor/base.py
flask_auditor/config.py
flask_auditor/request.py
flask_auditor/response.py
flask_auditor-0.2.1.dist-info/LICENSE
flask_auditor-0.2.1.dist-info/METADATA
flask_auditor-0.2.1.dist-info/WHEEL
flask_auditor-0.2.1.dist-info/top_level.txt
flask_auditor-0.2.1.dist-info/RECORD
