Metadata-Version: 2.1
Name: flask-auditor
Version: 0.2.1
Summary: An extension for Flask application to extract audit logs.
Author-email: Kai Nguyen <tronghaibk2008@gmail.com>
Maintainer-email: Kai Nguyen <tronghaibk2008@gmail.com>
Project-URL: Homepage, https://github.com/tniah/flask-audit-log
Project-URL: Issues, https://github.com/tniah/flask-audit-log/issues
Classifier: Programming Language :: Python :: 3
Classifier: License :: OSI Approved :: Apache Software License
Classifier: Operating System :: OS Independent
Classifier: Framework :: Flask
Requires-Python: >=3.8
License-File: LICENSE
Requires-Dist: flask >=2.3.0
Provides-Extra: test
Requires-Dist: pytest >=8.2.1 ; extra == 'test'
